MANIFEST.in
setup.py
helm_template_generator/args.py
helm_template_generator/generator.py
helm_template_generator.egg-info/PKG-INFO
helm_template_generator.egg-info/SOURCES.txt
helm_template_generator.egg-info/dependency_links.txt
helm_template_generator.egg-info/entry_points.txt
helm_template_generator.egg-info/not-zip-safe
helm_template_generator.egg-info/requires.txt
helm_template_generator.egg-info/top_level.txt
helm_template_generator/templates/Chart.tmpl.yaml
helm_template_generator/templates/NOTES.tmpl.txt
helm_template_generator/templates/_helpers.tmpl.tpl
helm_template_generator/templates/deployment.tmpl.yaml
helm_template_generator/templates/ingress.tmpl.yaml
helm_template_generator/templates/init-config-map.tmpl.yaml
helm_template_generator/templates/nginx-config-map.tmpl.yaml
helm_template_generator/templates/service.tmpl.yaml